fsd_heroku/__init__.py
fsd_heroku/deploy.py
fsd_heroku/deploy_messages.py
fsd_heroku/platform_deployer.py
fsd_heroku/plugin_config.py
fsd_heroku-0.0.1.dist-info/METADATA
fsd_heroku-0.0.1.dist-info/WHEEL
fsd_heroku-0.0.1.dist-info/top_level.txt
fsd_heroku-0.0.1.dist-info/RECORD
